monosurf/__init__.py
monosurf/client.py
monosurf/endpoints.py
monosurf/schemas.py
monosurf/settings.py
monosurf-0.3.1.dist-info/METADATA
monosurf-0.3.1.dist-info/WHEEL
monosurf-0.3.1.dist-info/RECORD
